KubernetesZhongwenZhinanYunYuanshengYingyongJiagouShijianShouceFix1/README.md
KubernetesZhongwenZhinanYunYuanshengYingyongJiagouShijianShouceFix1/__init__.py
KubernetesZhongwenZhinanYunYuanshengYingyongJiagouShijianShouceFix1/__main__.py
KubernetesZhongwenZhinanYunYuanshengYingyongJiagouShijianShouceFix1/file.epub
KubernetesZhongwenZhinanYunYuanshengYingyongJiagouShijianShouceFix1/index.html
KubernetesZhongwenZhinanYunYuanshengYingyongJiagouShijianShouceFix1/css/__init__.py
KubernetesZhongwenZhinanYunYuanshengYingyongJiagouShijianShouceFix1/css/annotations.css
KubernetesZhongwenZhinanYunYuanshengYingyongJiagouShijianShouceFix1/css/main.css
KubernetesZhongwenZhinanYunYuanshengYingyongJiagouShijianShouceFix1/css/normalize.css
KubernetesZhongwenZhinanYunYuanshengYingyongJiagouShijianShouceFix1/css/popup.css
KubernetesZhongwenZhinanYunYuanshengYingyongJiagouShijianShouceFix1/font/__init__.py
KubernetesZhongwenZhinanYunYuanshengYingyongJiagouShijianShouceFix1/font/fontello.eot
KubernetesZhongwenZhinanYunYuanshengYingyongJiagouShijianShouceFix1/font/fontello.svg
KubernetesZhongwenZhinanYunYuanshengYingyongJiagouShijianShouceFix1/font/fontello.ttf
KubernetesZhongwenZhinanYunYuanshengYingyongJiagouShijianShouceFix1/font/fontello.woff
KubernetesZhongwenZhinanYunYuanshengYingyongJiagouShijianShouceFix1/img/__init__.py
KubernetesZhongwenZhinanYunYuanshengYingyongJiagouShijianShouceFix1/img/annotator-glyph-sprite.png
KubernetesZhongwenZhinanYunYuanshengYingyongJiagouShijianShouceFix1/img/annotator-icon-sprite.png
KubernetesZhongwenZhinanYunYuanshengYingyongJiagouShijianShouceFix1/img/apple-touch-icon.png
KubernetesZhongwenZhinanYunYuanshengYingyongJiagouShijianShouceFix1/img/cancelfullscreen.png
KubernetesZhongwenZhinanYunYuanshengYingyongJiagouShijianShouceFix1/img/close.png
KubernetesZhongwenZhinanYunYuanshengYingyongJiagouShijianShouceFix1/img/fullscreen.png
KubernetesZhongwenZhinanYunYuanshengYingyongJiagouShijianShouceFix1/img/loader.gif
kubernetes_zhongwen_zhinan_yun_yuansheng_yingyong_jiagou_shijian_shouce_fix1-2025.3.25.0.dist-info/METADATA
kubernetes_zhongwen_zhinan_yun_yuansheng_yingyong_jiagou_shijian_shouce_fix1-2025.3.25.0.dist-info/WHEEL
kubernetes_zhongwen_zhinan_yun_yuansheng_yingyong_jiagou_shijian_shouce_fix1-2025.3.25.0.dist-info/entry_points.txt
kubernetes_zhongwen_zhinan_yun_yuansheng_yingyong_jiagou_shijian_shouce_fix1-2025.3.25.0.dist-info/top_level.txt
kubernetes_zhongwen_zhinan_yun_yuansheng_yingyong_jiagou_shijian_shouce_fix1-2025.3.25.0.dist-info/RECORD
